pytest_plone/__init__.py
pytest_plone/helpers.py
pytest_plone/fixtures/__init__.py
pytest_plone/fixtures/addons.py
pytest_plone/fixtures/base.py
pytest_plone/fixtures/content.py
pytest_plone/fixtures/env.py
pytest_plone/fixtures/vocabularies.py
pytest_plone-0.5.0.dist-info/LICENSE.GPL
pytest_plone-0.5.0.dist-info/METADATA
pytest_plone-0.5.0.dist-info/WHEEL
pytest_plone-0.5.0.dist-info/entry_points.txt
pytest_plone-0.5.0.dist-info/top_level.txt
pytest_plone-0.5.0.dist-info/RECORD
