Metadata-Version: 2.1
Name: pytest-plone
Version: 0.5.0
Summary: Pytest plugin to test Plone addons
Home-page: http://pypi.python.org/pypi/pytest-plone
Author: Plone
Author-email: test@plone.org
License: GPL
Project-URL: PyPI, https://pypi.python.org/pypi/pytest-plone
Project-URL: Source, https://github.com/collective/pytest-plone
Project-URL: Tracker, https://github.com/collective/pytest-plone/issues
Keywords: Plone Pytest Testing
Classifier: Development Status :: 3 - Alpha
Classifier: Framework :: Plone
Classifier: Framework :: Plone :: 6.0
Classifier: Framework :: Pytest
Classifier: Intended Audience :: Developers
Classifier: License :: OSI Approved :: GNU General Public License v2 (GPLv2)
Classifier: Operating System :: OS Independent
Classifier: Programming Language :: Python :: 3.8
Classifier: Programming Language :: Python :: 3.9
Classifier: Programming Language :: Python :: 3.10
Classifier: Programming Language :: Python :: 3.11
Classifier: Programming Language :: Python :: 3.12
Classifier: Programming Language :: Python :: 3
Classifier: Programming Language :: Python
Classifier: Topic :: Software Development :: Testing
Requires-Python: >=3.8
License-File: LICENSE.GPL
Requires-Dist: zope.pytestlayer
Requires-Dist: plone.api
Requires-Dist: plone.app.testing
Requires-Dist: plone.base
Requires-Dist: plone.browserlayer
Requires-Dist: plone.dexterity
Requires-Dist: Products.CMFPlone
Requires-Dist: pytest <8.0.0
Requires-Dist: setuptools
Requires-Dist: zope.component
Requires-Dist: zope.schema
Provides-Extra: test
Requires-Dist: zest.releaser[recommended] ; extra == 'test'
Requires-Dist: zestreleaser.towncrier ; extra == 'test'
Requires-Dist: pytest-cov ; extra == 'test'
